README.md
package_info.json
setup.py
th2_grpc_woodpecker/__init__.py
th2_grpc_woodpecker/py.typed
th2_grpc_woodpecker/woodpecker.proto
th2_grpc_woodpecker/woodpecker_pb2.py
th2_grpc_woodpecker/woodpecker_pb2.pyi
th2_grpc_woodpecker/woodpecker_pb2_grpc.py
th2_grpc_woodpecker/woodpecker_service.py
th2_grpc_woodpecker.egg-info/PKG-INFO
th2_grpc_woodpecker.egg-info/SOURCES.txt
th2_grpc_woodpecker.egg-info/dependency_links.txt
th2_grpc_woodpecker.egg-info/requires.txt
th2_grpc_woodpecker.egg-info/top_level.txt